Algopylib/__init__.py
Algopylib/algo/__init__.py
Algopylib/algo/binary.py
Algopylib/algo/check.py
Algopylib/algo/sort.py
Algopylib/math/__init__.py
Algopylib/math/combinatorics.py
Algopylib/math/gcd_lcm.py
Algopylib/math/geometry.py
Algopylib/math/matrix.py
Algopylib/math/series.py
Algopylib/math/stat.py
Algopylib/puzzle/__init__.py
Algopylib/puzzle/sudoku.py
Algopylib/puzzle/tictaktoe.py
Algopylib-0.0.3.dist-info/LICENSE.txt
Algopylib-0.0.3.dist-info/METADATA
Algopylib-0.0.3.dist-info/WHEEL
Algopylib-0.0.3.dist-info/top_level.txt
Algopylib-0.0.3.dist-info/RECORD
