Metadata-Version: 2.1
Name: Algopylib
Version: 0.0.3
Summary: A basic python library that has modules for maths and algorithms 
Home-page: https://github.com/still-n0thing/Algopylib
Author: Anisha Agrawal, Dhaval Kumar and Shivam Saxena
Author-email: iiitalgopy@googlegroups.com
License: UNKNOWN
Project-URL: Bug Tracker, https://github.com/still-n0thing/Algopylib/issues
Platform: UNKNOWN
Classifier: Programming Language :: Python :: 3
Classifier: License :: OSI Approved :: MIT License
Classifier: Operating System :: OS Independent
Requires-Python: >=3.7
